{
  "schemaVersion": 1,
  "school": {
    "name": "VPPS (sample)"
  },
  "teachers": [
    {
      "id": "Bindu",
      "name": "Bindu",
      "subjects": [
        "ELGA",
        "Maths",
        "EVS",
        "Hindi"
      ],
      "maxPeriodsPerDay": 6,
      "maxPeriodsPerWeek": 36,
      "unavailable": []
    },
    {
      "id": "Anita",
      "name": "Anita",
      "subjects": [
        "ELGA",
        "Hindi",
        "Maths",
        "EVS"
      ],
      "maxPeriodsPerDay": 6,
      "maxPeriodsPerWeek": 36,
      "unavailable": []
    },
    {
      "id": "Rashmita",
      "name": "Rashmita",
      "subjects": [
        "ELGA",
        "Hindi",
        "Maths",
        "EVS"
      ],
      "maxPeriodsPerDay": 6,
      "maxPeriodsPerWeek": 36,
      "unavailable": []
    },
    {
      "id": "Kusum",
      "name": "Kusum",
      "subjects": [
        "ELGA",
        "Hindi",
        "Maths",
        "EVS"
      ],
      "maxPeriodsPerDay": 6,
      "maxPeriodsPerWeek": 36,
      "unavailable": []
    },
    {
      "id": "Ravina",
      "name": "Ravina",
      "subjects": [
        "ELGA",
        "EVS",
        "Hindi",
        "Maths"
      ],
      "maxPeriodsPerDay": 6,
      "maxPeriodsPerWeek": 36,
      "unavailable": []
    },
    {
      "id": "Nidhika",
      "name": "Nidhika",
      "subjects": [
        "Maths"
      ],
      "maxPeriodsPerDay": 6,
      "maxPeriodsPerWeek": 36,
      "unavailable": []
    },
    {
      "id": "Mahesh",
      "name": "Mahesh",
      "subjects": [
        "Science"
      ],
      "maxPeriodsPerDay": 6,
      "maxPeriodsPerWeek": 36,
      "unavailable": []
    },
    {
      "id": "Anjana",
      "name": "Anjana",
      "subjects": [
        "Hindi"
      ],
      "maxPeriodsPerDay": 6,
      "maxPeriodsPerWeek": 36,
      "unavailable": []
    },
    {
      "id": "Harshita",
      "name": "Harshita",
      "subjects": [
        "English"
      ],
      "maxPeriodsPerDay": 6,
      "maxPeriodsPerWeek": 36,
      "unavailable": []
    },
    {
      "id": "Toshit",
      "name": "Toshit",
      "subjects": [
        "Social Science"
      ],
      "maxPeriodsPerDay": 6,
      "maxPeriodsPerWeek": 36,
      "unavailable": []
    },
    {
      "id": "Pradhyuman",
      "name": "Pradhyuman",
      "subjects": [
        "Physics"
      ],
      "maxPeriodsPerDay": 6,
      "maxPeriodsPerWeek": 36,
      "unavailable": []
    },
    {
      "id": "Prakash",
      "name": "Prakash",
      "subjects": [
        "Chemistry"
      ],
      "maxPeriodsPerDay": 6,
      "maxPeriodsPerWeek": 36,
      "unavailable": []
    },
    {
      "id": "Jainendra",
      "name": "Jainendra",
      "subjects": [
        "Biology"
      ],
      "maxPeriodsPerDay": 6,
      "maxPeriodsPerWeek": 36,
      "unavailable": []
    },
    {
      "id": "Rakesh",
      "name": "Rakesh",
      "subjects": [
        "Maths"
      ],
      "maxPeriodsPerDay": 6,
      "maxPeriodsPerWeek": 36,
      "unavailable": []
    },
    {
      "id": "Hemlata",
      "name": "Hemlata",
      "subjects": [
        "English"
      ],
      "maxPeriodsPerDay": 6,
      "maxPeriodsPerWeek": 36,
      "unavailable": []
    }
  ],
  "classes": [
    {
      "id": "Class 1",
      "name": "Class 1",
      "group": "primary"
    },
    {
      "id": "Class 2",
      "name": "Class 2",
      "group": "primary"
    },
    {
      "id": "Class 3",
      "name": "Class 3",
      "group": "primary"
    },
    {
      "id": "Class 4",
      "name": "Class 4",
      "group": "primary"
    },
    {
      "id": "Class 5",
      "name": "Class 5",
      "group": "primary"
    },
    {
      "id": "Class 7",
      "name": "Class 7",
      "group": "middle"
    },
    {
      "id": "Class 11 Science",
      "name": "Class 11 Science",
      "group": "senior"
    }
  ],
  "subjects": [
    {
      "id": "ELGA",
      "name": "ELGA"
    },
    {
      "id": "Maths",
      "name": "Maths"
    },
    {
      "id": "Hindi",
      "name": "Hindi"
    },
    {
      "id": "EVS",
      "name": "EVS"
    },
    {
      "id": "Science",
      "name": "Science"
    },
    {
      "id": "English",
      "name": "English"
    },
    {
      "id": "Social Science",
      "name": "Social Science"
    },
    {
      "id": "Physics",
      "name": "Physics"
    },
    {
      "id": "Chemistry",
      "name": "Chemistry"
    },
    {
      "id": "Biology",
      "name": "Biology"
    }
  ],
  "profiles": [
    {
      "id": "imported",
      "name": "imported",
      "days": [
        "Mon",
        "Tue"
      ],
      "periods": [
        {
          "label": "P1",
          "start": "",
          "end": ""
        },
        {
          "label": "P2",
          "start": "",
          "end": ""
        },
        {
          "label": "P3",
          "start": "",
          "end": ""
        },
        {
          "label": "P4",
          "start": "",
          "end": ""
        },
        {
          "label": "P5",
          "start": "",
          "end": ""
        },
        {
          "label": "P6",
          "start": "",
          "end": ""
        }
      ]
    }
  ],
  "activities": [
    {
      "kind": "block",
      "id": "block-elga-0",
      "name": "ELGA",
      "classIds": [
        "Class 1",
        "Class 2",
        "Class 3",
        "Class 4",
        "Class 5"
      ],
      "teacherIds": [
        "Bindu",
        "Anita",
        "Rashmita",
        "Kusum",
        "Ravina"
      ],
      "length": 3
    },
    {
      "kind": "lesson",
      "id": "L|Class 1|Mon|1",
      "classId": "Class 1",
      "subjectId": "Maths",
      "teacherIds": [
        "Bindu"
      ]
    },
    {
      "kind": "lesson",
      "id": "L|Class 1|Mon|2",
      "classId": "Class 1",
      "subjectId": "Hindi",
      "teacherIds": [
        "Anita"
      ]
    },
    {
      "kind": "lesson",
      "id": "L|Class 1|Mon|6",
      "classId": "Class 1",
      "subjectId": "EVS",
      "teacherIds": [
        "Ravina"
      ]
    },
    {
      "kind": "lesson",
      "id": "L|Class 1|Tue|1",
      "classId": "Class 1",
      "subjectId": "Maths",
      "teacherIds": [
        "Bindu"
      ]
    },
    {
      "kind": "lesson",
      "id": "L|Class 1|Tue|2",
      "classId": "Class 1",
      "subjectId": "Hindi",
      "teacherIds": [
        "Anita"
      ]
    },
    {
      "kind": "lesson",
      "id": "L|Class 1|Tue|6",
      "classId": "Class 1",
      "subjectId": "EVS",
      "teacherIds": [
        "Ravina"
      ]
    },
    {
      "kind": "lesson",
      "id": "L|Class 2|Mon|1",
      "classId": "Class 2",
      "subjectId": "Maths",
      "teacherIds": [
        "Anita"
      ]
    },
    {
      "kind": "lesson",
      "id": "L|Class 2|Mon|2",
      "classId": "Class 2",
      "subjectId": "Hindi",
      "teacherIds": [
        "Rashmita"
      ]
    },
    {
      "kind": "lesson",
      "id": "L|Class 2|Mon|6",
      "classId": "Class 2",
      "subjectId": "EVS",
      "teacherIds": [
        "Bindu"
      ]
    },
    {
      "kind": "lesson",
      "id": "L|Class 2|Tue|1",
      "classId": "Class 2",
      "subjectId": "Maths",
      "teacherIds": [
        "Anita"
      ]
    },
    {
      "kind": "lesson",
      "id": "L|Class 2|Tue|2",
      "classId": "Class 2",
      "subjectId": "Hindi",
      "teacherIds": [
        "Rashmita"
      ]
    },
    {
      "kind": "lesson",
      "id": "L|Class 2|Tue|6",
      "classId": "Class 2",
      "subjectId": "EVS",
      "teacherIds": [
        "Bindu"
      ]
    },
    {
      "kind": "lesson",
      "id": "L|Class 3|Mon|1",
      "classId": "Class 3",
      "subjectId": "Maths",
      "teacherIds": [
        "Rashmita"
      ]
    },
    {
      "kind": "lesson",
      "id": "L|Class 3|Mon|2",
      "classId": "Class 3",
      "subjectId": "Hindi",
      "teacherIds": [
        "Kusum"
      ]
    },
    {
      "kind": "lesson",
      "id": "L|Class 3|Mon|6",
      "classId": "Class 3",
      "subjectId": "EVS",
      "teacherIds": [
        "Anita"
      ]
    },
    {
      "kind": "lesson",
      "id": "L|Class 3|Tue|1",
      "classId": "Class 3",
      "subjectId": "Maths",
      "teacherIds": [
        "Rashmita"
      ]
    },
    {
      "kind": "lesson",
      "id": "L|Class 3|Tue|2",
      "classId": "Class 3",
      "subjectId": "Hindi",
      "teacherIds": [
        "Kusum"
      ]
    },
    {
      "kind": "lesson",
      "id": "L|Class 3|Tue|6",
      "classId": "Class 3",
      "subjectId": "EVS",
      "teacherIds": [
        "Anita"
      ]
    },
    {
      "kind": "lesson",
      "id": "L|Class 4|Mon|1",
      "classId": "Class 4",
      "subjectId": "Maths",
      "teacherIds": [
        "Kusum"
      ]
    },
    {
      "kind": "lesson",
      "id": "L|Class 4|Mon|2",
      "classId": "Class 4",
      "subjectId": "Hindi",
      "teacherIds": [
        "Ravina"
      ]
    },
    {
      "kind": "lesson",
      "id": "L|Class 4|Mon|6",
      "classId": "Class 4",
      "subjectId": "EVS",
      "teacherIds": [
        "Rashmita"
      ]
    },
    {
      "kind": "lesson",
      "id": "L|Class 4|Tue|1",
      "classId": "Class 4",
      "subjectId": "Maths",
      "teacherIds": [
        "Kusum"
      ]
    },
    {
      "kind": "lesson",
      "id": "L|Class 4|Tue|2",
      "classId": "Class 4",
      "subjectId": "Hindi",
      "teacherIds": [
        "Ravina"
      ]
    },
    {
      "kind": "lesson",
      "id": "L|Class 4|Tue|6",
      "classId": "Class 4",
      "subjectId": "EVS",
      "teacherIds": [
        "Rashmita"
      ]
    },
    {
      "kind": "lesson",
      "id": "L|Class 5|Mon|1",
      "classId": "Class 5",
      "subjectId": "Maths",
      "teacherIds": [
        "Ravina"
      ]
    },
    {
      "kind": "lesson",
      "id": "L|Class 5|Mon|2",
      "classId": "Class 5",
      "subjectId": "Hindi",
      "teacherIds": [
        "Bindu"
      ]
    },
    {
      "kind": "lesson",
      "id": "L|Class 5|Mon|6",
      "classId": "Class 5",
      "subjectId": "EVS",
      "teacherIds": [
        "Kusum"
      ]
    },
    {
      "kind": "lesson",
      "id": "L|Class 5|Tue|1",
      "classId": "Class 5",
      "subjectId": "Maths",
      "teacherIds": [
        "Ravina"
      ]
    },
    {
      "kind": "lesson",
      "id": "L|Class 5|Tue|2",
      "classId": "Class 5",
      "subjectId": "Hindi",
      "teacherIds": [
        "Bindu"
      ]
    },
    {
      "kind": "lesson",
      "id": "L|Class 5|Tue|6",
      "classId": "Class 5",
      "subjectId": "EVS",
      "teacherIds": [
        "Kusum"
      ]
    },
    {
      "kind": "lesson",
      "id": "L|Class 7|Mon|1",
      "classId": "Class 7",
      "subjectId": "Maths",
      "teacherIds": [
        "Nidhika"
      ]
    },
    {
      "kind": "lesson",
      "id": "L|Class 7|Mon|2",
      "classId": "Class 7",
      "subjectId": "Science",
      "teacherIds": [
        "Mahesh"
      ]
    },
    {
      "kind": "lesson",
      "id": "L|Class 7|Mon|3",
      "classId": "Class 7",
      "subjectId": "Hindi",
      "teacherIds": [
        "Anjana"
      ]
    },
    {
      "kind": "lesson",
      "id": "L|Class 7|Mon|4",
      "classId": "Class 7",
      "subjectId": "English",
      "teacherIds": [
        "Harshita"
      ]
    },
    {
      "kind": "lesson",
      "id": "L|Class 7|Mon|5",
      "classId": "Class 7",
      "subjectId": "Social Science",
      "teacherIds": [
        "Toshit"
      ]
    },
    {
      "kind": "lesson",
      "id": "L|Class 7|Mon|6",
      "classId": "Class 7",
      "subjectId": "Maths",
      "teacherIds": [
        "Nidhika"
      ]
    },
    {
      "kind": "lesson",
      "id": "L|Class 7|Tue|1",
      "classId": "Class 7",
      "subjectId": "Maths",
      "teacherIds": [
        "Nidhika"
      ]
    },
    {
      "kind": "lesson",
      "id": "L|Class 7|Tue|2",
      "classId": "Class 7",
      "subjectId": "Science",
      "teacherIds": [
        "Mahesh"
      ]
    },
    {
      "kind": "lesson",
      "id": "L|Class 7|Tue|3",
      "classId": "Class 7",
      "subjectId": "Hindi",
      "teacherIds": [
        "Anjana"
      ]
    },
    {
      "kind": "lesson",
      "id": "L|Class 7|Tue|4",
      "classId": "Class 7",
      "subjectId": "English",
      "teacherIds": [
        "Harshita"
      ]
    },
    {
      "kind": "lesson",
      "id": "L|Class 7|Tue|5",
      "classId": "Class 7",
      "subjectId": "Social Science",
      "teacherIds": [
        "Toshit"
      ]
    },
    {
      "kind": "lesson",
      "id": "L|Class 7|Tue|6",
      "classId": "Class 7",
      "subjectId": "Maths",
      "teacherIds": [
        "Nidhika"
      ]
    },
    {
      "kind": "lesson",
      "id": "L|Class 11 Science|Mon|1",
      "classId": "Class 11 Science",
      "subjectId": "Physics",
      "teacherIds": [
        "Pradhyuman"
      ]
    },
    {
      "kind": "lesson",
      "id": "L|Class 11 Science|Mon|2",
      "classId": "Class 11 Science",
      "subjectId": "Chemistry",
      "teacherIds": [
        "Prakash"
      ]
    },
    {
      "kind": "lesson",
      "id": "L|Class 11 Science|Mon|3",
      "classId": "Class 11 Science",
      "subjectId": "Biology",
      "teacherIds": [
        "Jainendra"
      ]
    },
    {
      "kind": "lesson",
      "id": "L|Class 11 Science|Mon|4",
      "classId": "Class 11 Science",
      "subjectId": "Maths",
      "teacherIds": [
        "Rakesh"
      ]
    },
    {
      "kind": "lesson",
      "id": "L|Class 11 Science|Mon|5",
      "classId": "Class 11 Science",
      "subjectId": "English",
      "teacherIds": [
        "Hemlata"
      ]
    },
    {
      "kind": "lesson",
      "id": "L|Class 11 Science|Tue|1",
      "classId": "Class 11 Science",
      "subjectId": "Physics",
      "teacherIds": [
        "Pradhyuman"
      ]
    },
    {
      "kind": "lesson",
      "id": "L|Class 11 Science|Tue|2",
      "classId": "Class 11 Science",
      "subjectId": "Chemistry",
      "teacherIds": [
        "Prakash"
      ]
    },
    {
      "kind": "lesson",
      "id": "L|Class 11 Science|Tue|3",
      "classId": "Class 11 Science",
      "subjectId": "Biology",
      "teacherIds": [
        "Jainendra"
      ]
    },
    {
      "kind": "lesson",
      "id": "L|Class 11 Science|Tue|4",
      "classId": "Class 11 Science",
      "subjectId": "Maths",
      "teacherIds": [
        "Rakesh"
      ]
    },
    {
      "kind": "lesson",
      "id": "L|Class 11 Science|Tue|5",
      "classId": "Class 11 Science",
      "subjectId": "English",
      "teacherIds": [
        "Hemlata"
      ]
    }
  ],
  "requirements": {
    "curriculum": [],
    "blocks": []
  },
  "timetables": [
    {
      "id": "imported",
      "name": "VPPS (sample)",
      "profileId": "imported",
      "placements": [
        {
          "activityId": "block-elga-0",
          "day": "Mon",
          "period": 3,
          "pinned": true
        },
        {
          "activityId": "block-elga-0",
          "day": "Tue",
          "period": 3,
          "pinned": true
        },
        {
          "activityId": "L|Class 1|Mon|1",
          "day": "Mon",
          "period": 1,
          "pinned": false
        },
        {
          "activityId": "L|Class 1|Mon|2",
          "day": "Mon",
          "period": 2,
          "pinned": false
        },
        {
          "activityId": "L|Class 1|Mon|6",
          "day": "Mon",
          "period": 6,
          "pinned": false
        },
        {
          "activityId": "L|Class 1|Tue|1",
          "day": "Tue",
          "period": 1,
          "pinned": false
        },
        {
          "activityId": "L|Class 1|Tue|2",
          "day": "Tue",
          "period": 2,
          "pinned": false
        },
        {
          "activityId": "L|Class 1|Tue|6",
          "day": "Tue",
          "period": 6,
          "pinned": false
        },
        {
          "activityId": "L|Class 2|Mon|1",
          "day": "Mon",
          "period": 1,
          "pinned": false
        },
        {
          "activityId": "L|Class 2|Mon|2",
          "day": "Mon",
          "period": 2,
          "pinned": false
        },
        {
          "activityId": "L|Class 2|Mon|6",
          "day": "Mon",
          "period": 6,
          "pinned": false
        },
        {
          "activityId": "L|Class 2|Tue|1",
          "day": "Tue",
          "period": 1,
          "pinned": false
        },
        {
          "activityId": "L|Class 2|Tue|2",
          "day": "Tue",
          "period": 2,
          "pinned": false
        },
        {
          "activityId": "L|Class 2|Tue|6",
          "day": "Tue",
          "period": 6,
          "pinned": false
        },
        {
          "activityId": "L|Class 3|Mon|1",
          "day": "Mon",
          "period": 1,
          "pinned": false
        },
        {
          "activityId": "L|Class 3|Mon|2",
          "day": "Mon",
          "period": 2,
          "pinned": false
        },
        {
          "activityId": "L|Class 3|Mon|6",
          "day": "Mon",
          "period": 6,
          "pinned": false
        },
        {
          "activityId": "L|Class 3|Tue|1",
          "day": "Tue",
          "period": 1,
          "pinned": false
        },
        {
          "activityId": "L|Class 3|Tue|2",
          "day": "Tue",
          "period": 2,
          "pinned": false
        },
        {
          "activityId": "L|Class 3|Tue|6",
          "day": "Tue",
          "period": 6,
          "pinned": false
        },
        {
          "activityId": "L|Class 4|Mon|1",
          "day": "Mon",
          "period": 1,
          "pinned": false
        },
        {
          "activityId": "L|Class 4|Mon|2",
          "day": "Mon",
          "period": 2,
          "pinned": false
        },
        {
          "activityId": "L|Class 4|Mon|6",
          "day": "Mon",
          "period": 6,
          "pinned": false
        },
        {
          "activityId": "L|Class 4|Tue|1",
          "day": "Tue",
          "period": 1,
          "pinned": false
        },
        {
          "activityId": "L|Class 4|Tue|2",
          "day": "Tue",
          "period": 2,
          "pinned": false
        },
        {
          "activityId": "L|Class 4|Tue|6",
          "day": "Tue",
          "period": 6,
          "pinned": false
        },
        {
          "activityId": "L|Class 5|Mon|1",
          "day": "Mon",
          "period": 1,
          "pinned": false
        },
        {
          "activityId": "L|Class 5|Mon|2",
          "day": "Mon",
          "period": 2,
          "pinned": false
        },
        {
          "activityId": "L|Class 5|Mon|6",
          "day": "Mon",
          "period": 6,
          "pinned": false
        },
        {
          "activityId": "L|Class 5|Tue|1",
          "day": "Tue",
          "period": 1,
          "pinned": false
        },
        {
          "activityId": "L|Class 5|Tue|2",
          "day": "Tue",
          "period": 2,
          "pinned": false
        },
        {
          "activityId": "L|Class 5|Tue|6",
          "day": "Tue",
          "period": 6,
          "pinned": false
        },
        {
          "activityId": "L|Class 7|Mon|1",
          "day": "Mon",
          "period": 1,
          "pinned": false
        },
        {
          "activityId": "L|Class 7|Mon|2",
          "day": "Mon",
          "period": 2,
          "pinned": false
        },
        {
          "activityId": "L|Class 7|Mon|3",
          "day": "Mon",
          "period": 3,
          "pinned": false
        },
        {
          "activityId": "L|Class 7|Mon|4",
          "day": "Mon",
          "period": 4,
          "pinned": false
        },
        {
          "activityId": "L|Class 7|Mon|5",
          "day": "Mon",
          "period": 5,
          "pinned": false
        },
        {
          "activityId": "L|Class 7|Mon|6",
          "day": "Mon",
          "period": 6,
          "pinned": false
        },
        {
          "activityId": "L|Class 7|Tue|1",
          "day": "Tue",
          "period": 1,
          "pinned": false
        },
        {
          "activityId": "L|Class 7|Tue|2",
          "day": "Tue",
          "period": 2,
          "pinned": false
        },
        {
          "activityId": "L|Class 7|Tue|3",
          "day": "Tue",
          "period": 3,
          "pinned": false
        },
        {
          "activityId": "L|Class 7|Tue|4",
          "day": "Tue",
          "period": 4,
          "pinned": false
        },
        {
          "activityId": "L|Class 7|Tue|5",
          "day": "Tue",
          "period": 5,
          "pinned": false
        },
        {
          "activityId": "L|Class 7|Tue|6",
          "day": "Tue",
          "period": 6,
          "pinned": false
        },
        {
          "activityId": "L|Class 11 Science|Mon|1",
          "day": "Mon",
          "period": 1,
          "pinned": false
        },
        {
          "activityId": "L|Class 11 Science|Mon|2",
          "day": "Mon",
          "period": 2,
          "pinned": false
        },
        {
          "activityId": "L|Class 11 Science|Mon|3",
          "day": "Mon",
          "period": 3,
          "pinned": false
        },
        {
          "activityId": "L|Class 11 Science|Mon|4",
          "day": "Mon",
          "period": 4,
          "pinned": false
        },
        {
          "activityId": "L|Class 11 Science|Mon|5",
          "day": "Mon",
          "period": 5,
          "pinned": false
        },
        {
          "activityId": "L|Class 11 Science|Tue|1",
          "day": "Tue",
          "period": 1,
          "pinned": false
        },
        {
          "activityId": "L|Class 11 Science|Tue|2",
          "day": "Tue",
          "period": 2,
          "pinned": false
        },
        {
          "activityId": "L|Class 11 Science|Tue|3",
          "day": "Tue",
          "period": 3,
          "pinned": false
        },
        {
          "activityId": "L|Class 11 Science|Tue|4",
          "day": "Tue",
          "period": 4,
          "pinned": false
        },
        {
          "activityId": "L|Class 11 Science|Tue|5",
          "day": "Tue",
          "period": 5,
          "pinned": false
        }
      ]
    }
  ],
  "activeTimetableId": "imported"
}
